[
  {
    "model": "auth.user",
    "pk": 3,
    "fields": {
      "password": "pbkdf2_sha256$36000$nKtmEKeobIqK$J3S4PKE3eJjRsA0z8xWo05OdrULMA9El5HSiWlqXNCw=",
      "last_login": "2017-05-31T20:46:26.344Z",
      "is_superuser": false,
      "username": "Axl",
      "first_name": "",
      "last_name": "",
      "email": "",
      "is_staff": true,
      "is_active": true,
      "date_joined": "2017-05-31T20:23:20Z",
      "groups": [],
      "user_permissions": []
    }
  },
  {
    "model": "auth.user",
    "pk": 4,
    "fields": {
      "password": "pbkdf2_sha256$36000$nKtmEKeobIqK$J3S4PKE3eJjRsA0z8xWo05OdrULMA9El5HSiWlqXNCw=",
      "last_login": "2017-05-31T20:46:26.344Z",
      "is_superuser": false,
      "username": "Madness",
      "first_name": "",
      "last_name": "",
      "email": "",
      "is_staff": true,
      "is_active": true,
      "date_joined": "2017-05-31T20:23:20Z",
      "groups": [],
      "user_permissions": []
    }
  },
  {
    "model": "auth.user",
    "pk": 5,
    "fields": {
      "password": "pbkdf2_sha256$36000$nKtmEKeobIqK$J3S4PKE3eJjRsA0z8xWo05OdrULMA9El5HSiWlqXNCw=",
      "last_login": "2017-05-31T20:46:26.344Z",
      "is_superuser": false,
      "username": "zozo",
      "first_name": "",
      "last_name": "",
      "email": "",
      "is_staff": true,
      "is_active": true,
      "date_joined": "2017-05-31T20:23:20Z",
      "groups": [],
      "user_permissions": []
    }
  },
  {
    "model": "auth.user",
    "pk": 6,
    "fields": {
      "password": "pbkdf2_sha256$36000$nKtmEKeobIqK$J3S4PKE3eJjRsA0z8xWo05OdrULMA9El5HSiWlqXNCw=",
      "last_login": "2017-05-31T20:46:26.344Z",
      "is_superuser": false,
      "username": "Fier Panpan",
      "first_name": "",
      "last_name": "",
      "email": "",
      "is_staff": true,
      "is_active": true,
      "date_joined": "2017-05-31T20:23:20Z",
      "groups": [],
      "user_permissions": []
    }
  },
  {
    "model": "auth.user",
    "pk": 7,
    "fields": {
      "password": "pbkdf2_sha256$36000$nKtmEKeobIqK$J3S4PKE3eJjRsA0z8xWo05OdrULMA9El5HSiWlqXNCw=",
      "last_login": "2017-05-31T20:46:26.344Z",
      "is_superuser": false,
      "username": "Olaf",
      "first_name": "",
      "last_name": "",
      "email": "",
      "is_staff": true,
      "is_active": true,
      "date_joined": "2017-05-31T20:23:20Z",
      "groups": [],
      "user_permissions": []
    }
  },
  {
    "model": "auth.user",
    "pk": 8,
    "fields": {
      "password": "pbkdf2_sha256$36000$nKtmEKeobIqK$J3S4PKE3eJjRsA0z8xWo05OdrULMA9El5HSiWlqXNCw=",
      "last_login": "2017-05-31T20:46:26.344Z",
      "is_superuser": false,
      "username": "baygonsec",
      "first_name": "",
      "last_name": "",
      "email": "",
      "is_staff": true,
      "is_active": true,
      "date_joined": "2017-05-31T20:23:20Z",
      "groups": [],
      "user_permissions": []
    }
  },
  {
    "model": "auth.user",
    "pk": 9,
    "fields": {
      "password": "pbkdf2_sha256$36000$nKtmEKeobIqK$J3S4PKE3eJjRsA0z8xWo05OdrULMA9El5HSiWlqXNCw=",
      "last_login": "2017-05-31T20:46:26.344Z",
      "is_superuser": false,
      "username": "El Brutal Principe",
      "first_name": "",
      "last_name": "",
      "email": "",
      "is_staff": true,
      "is_active": true,
      "date_joined": "2017-05-31T20:23:20Z",
      "groups": [],
      "user_permissions": []
    }
  },
  {
    "model": "auth.user",
    "pk": 10,
    "fields": {
      "password": "pbkdf2_sha256$36000$nKtmEKeobIqK$J3S4PKE3eJjRsA0z8xWo05OdrULMA9El5HSiWlqXNCw=",
      "last_login": "2017-05-31T20:46:26.344Z",
      "is_superuser": false,
      "username": "JeanBen",
      "first_name": "",
      "last_name": "",
      "email": "",
      "is_staff": true,
      "is_active": true,
      "date_joined": "2017-05-31T20:23:20Z",
      "groups": [],
      "user_permissions": []
    }
  },
  {
    "model": "auth.user",
    "pk": 11,
    "fields": {
      "password": "pbkdf2_sha256$36000$nKtmEKeobIqK$J3S4PKE3eJjRsA0z8xWo05OdrULMA9El5HSiWlqXNCw=",
      "last_login": "2017-05-31T20:46:26.344Z",
      "is_superuser": false,
      "username": "beLIEve",
      "first_name": "",
      "last_name": "",
      "email": "",
      "is_staff": true,
      "is_active": true,
      "date_joined": "2017-05-31T20:23:20Z",
      "groups": [],
      "user_permissions": []
    }
  },
  {
    "model": "auth.user",
    "pk": 12,
    "fields": {
      "password": "pbkdf2_sha256$36000$nKtmEKeobIqK$J3S4PKE3eJjRsA0z8xWo05OdrULMA9El5HSiWlqXNCw=",
      "last_login": "2017-05-31T20:46:26.344Z",
      "is_superuser": false,
      "username": "Flying Panda",
      "first_name": "",
      "last_name": "",
      "email": "",
      "is_staff": true,
      "is_active": true,
      "date_joined": "2017-05-31T20:23:20Z",
      "groups": [],
      "user_permissions": []
    }
  },
  {
    "model": "auth.user",
    "pk": 13,
    "fields": {
      "password": "pbkdf2_sha256$36000$nKtmEKeobIqK$J3S4PKE3eJjRsA0z8xWo05OdrULMA9El5HSiWlqXNCw=",
      "last_login": "2017-05-31T20:46:26.344Z",
      "is_superuser": false,
      "username": "Big Rach",
      "first_name": "",
      "last_name": "",
      "email": "",
      "is_staff": true,
      "is_active": true,
      "date_joined": "2017-05-31T20:23:20Z",
      "groups": [],
      "user_permissions": []
    }
  },
  {
    "model": "auth.user",
    "pk": 14,
    "fields": {
      "password": "pbkdf2_sha256$36000$nKtmEKeobIqK$J3S4PKE3eJjRsA0z8xWo05OdrULMA9El5HSiWlqXNCw=",
      "last_login": "2017-05-31T20:46:26.344Z",
      "is_superuser": false,
      "username": "Liv",
      "first_name": "",
      "last_name": "",
      "email": "",
      "is_staff": true,
      "is_active": true,
      "date_joined": "2017-05-31T20:23:20Z",
      "groups": [],
      "user_permissions": []
    }
  },
  {
    "model": "auth.user",
    "pk": 15,
    "fields": {
      "password": "pbkdf2_sha256$36000$nKtmEKeobIqK$J3S4PKE3eJjRsA0z8xWo05OdrULMA9El5HSiWlqXNCw=",
      "last_login": "2017-05-31T20:46:26.344Z",
      "is_superuser": false,
      "username": "Charlie Brown",
      "first_name": "",
      "last_name": "",
      "email": "",
      "is_staff": true,
      "is_active": true,
      "date_joined": "2017-05-31T20:23:20Z",
      "groups": [],
      "user_permissions": []
    }
  },
  {
    "model": "auth.user",
    "pk": 16,
    "fields": {
      "password": "pbkdf2_sha256$36000$nKtmEKeobIqK$J3S4PKE3eJjRsA0z8xWo05OdrULMA9El5HSiWlqXNCw=",
      "last_login": "2017-05-31T20:46:26.344Z",
      "is_superuser": false,
      "username": "Crampon",
      "first_name": "",
      "last_name": "",
      "email": "",
      "is_staff": true,
      "is_active": true,
      "date_joined": "2017-05-31T20:23:20Z",
      "groups": [],
      "user_permissions": []
    }
  },
  {
    "model": "auth.user",
    "pk": 17,
    "fields": {
      "password": "pbkdf2_sha256$36000$nKtmEKeobIqK$J3S4PKE3eJjRsA0z8xWo05OdrULMA9El5HSiWlqXNCw=",
      "last_login": "2017-05-31T20:46:26.344Z",
      "is_superuser": false,
      "username": "Tony Adams",
      "first_name": "",
      "last_name": "",
      "email": "",
      "is_staff": true,
      "is_active": true,
      "date_joined": "2017-05-31T20:23:20Z",
      "groups": [],
      "user_permissions": []
    }
  },
  {
    "model": "auth.user",
    "pk": 18,
    "fields": {
      "password": "pbkdf2_sha256$36000$nKtmEKeobIqK$J3S4PKE3eJjRsA0z8xWo05OdrULMA9El5HSiWlqXNCw=",
      "last_login": "2017-05-31T20:46:26.344Z",
      "is_superuser": false,
      "username": "Latrell",
      "first_name": "",
      "last_name": "",
      "email": "",
      "is_staff": true,
      "is_active": true,
      "date_joined": "2017-05-31T20:23:20Z",
      "groups": [],
      "user_permissions": []
    }
  },
  {
    "model": "auth.user",
    "pk": 19,
    "fields": {
      "password": "pbkdf2_sha256$36000$nKtmEKeobIqK$J3S4PKE3eJjRsA0z8xWo05OdrULMA9El5HSiWlqXNCw=",
      "last_login": "2017-05-31T20:46:26.344Z",
      "is_superuser": false,
      "username": "DNCG",
      "first_name": "",
      "last_name": "",
      "email": "",
      "is_staff": true,
      "is_active": true,
      "date_joined": "2017-05-31T20:23:20Z",
      "groups": [],
      "user_permissions": []
    }
  },
  {
    "model": "auth.user",
    "pk": 20,
    "fields": {
      "password": "pbkdf2_sha256$36000$nKtmEKeobIqK$J3S4PKE3eJjRsA0z8xWo05OdrULMA9El5HSiWlqXNCw=",
      "last_login": "2017-05-31T20:46:26.344Z",
      "is_superuser": false,
      "username": "Ze Mayor Queen",
      "first_name": "",
      "last_name": "",
      "email": "",
      "is_staff": true,
      "is_active": true,
      "date_joined": "2017-05-31T20:23:20Z",
      "groups": [],
      "user_permissions": []
    }
  },
  {
    "model": "auth.user",
    "pk": 21,
    "fields": {
      "password": "pbkdf2_sha256$36000$nKtmEKeobIqK$J3S4PKE3eJjRsA0z8xWo05OdrULMA9El5HSiWlqXNCw=",
      "last_login": "2017-05-31T20:46:26.344Z",
      "is_superuser": false,
      "username": "Leo",
      "first_name": "",
      "last_name": "",
      "email": "",
      "is_staff": true,
      "is_active": true,
      "date_joined": "2017-05-31T20:23:20Z",
      "groups": [],
      "user_permissions": []
    }
  },
  {
    "model": "auth.user",
    "pk": 22,
    "fields": {
      "password": "pbkdf2_sha256$36000$nKtmEKeobIqK$J3S4PKE3eJjRsA0z8xWo05OdrULMA9El5HSiWlqXNCw=",
      "last_login": "2017-05-31T20:46:26.344Z",
      "is_superuser": false,
      "username": "surlac",
      "first_name": "",
      "last_name": "",
      "email": "",
      "is_staff": true,
      "is_active": true,
      "date_joined": "2017-05-31T20:23:20Z",
      "groups": [],
      "user_permissions": []
    }
  },
  {
    "model": "auth.user",
    "pk": 23,
    "fields": {
      "password": "pbkdf2_sha256$36000$nKtmEKeobIqK$J3S4PKE3eJjRsA0z8xWo05OdrULMA9El5HSiWlqXNCw=",
      "last_login": "2017-05-31T20:46:26.344Z",
      "is_superuser": false,
      "username": "boistou",
      "first_name": "",
      "last_name": "",
      "email": "",
      "is_staff": true,
      "is_active": true,
      "date_joined": "2017-05-31T20:23:20Z",
      "groups": [],
      "user_permissions": []
    }
  },
  {
    "model": "auth.user",
    "pk": 24,
    "fields": {
      "password": "pbkdf2_sha256$36000$nKtmEKeobIqK$J3S4PKE3eJjRsA0z8xWo05OdrULMA9El5HSiWlqXNCw=",
      "last_login": "2017-05-31T20:46:26.344Z",
      "is_superuser": false,
      "username": "Brouche",
      "first_name": "",
      "last_name": "",
      "email": "",
      "is_staff": true,
      "is_active": true,
      "date_joined": "2017-05-31T20:23:20Z",
      "groups": [],
      "user_permissions": []
    }
  },
  {
    "model": "auth.user",
    "pk": 25,
    "fields": {
      "password": "pbkdf2_sha256$36000$nKtmEKeobIqK$J3S4PKE3eJjRsA0z8xWo05OdrULMA9El5HSiWlqXNCw=",
      "last_login": "2017-05-31T20:46:26.344Z",
      "is_superuser": false,
      "username": "bomba",
      "first_name": "",
      "last_name": "",
      "email": "",
      "is_staff": true,
      "is_active": true,
      "date_joined": "2017-05-31T20:23:20Z",
      "groups": [],
      "user_permissions": []
    }
  },
  {
    "model": "auth.user",
    "pk": 26,
    "fields": {
      "password": "pbkdf2_sha256$36000$nKtmEKeobIqK$J3S4PKE3eJjRsA0z8xWo05OdrULMA9El5HSiWlqXNCw=",
      "last_login": "2017-05-31T20:46:26.344Z",
      "is_superuser": false,
      "username": "Gilliatt",
      "first_name": "",
      "last_name": "",
      "email": "",
      "is_staff": true,
      "is_active": true,
      "date_joined": "2017-05-31T20:23:20Z",
      "groups": [],
      "user_permissions": []
    }
  },
  {
    "model": "auth.user",
    "pk": 27,
    "fields": {
      "password": "pbkdf2_sha256$36000$nKtmEKeobIqK$J3S4PKE3eJjRsA0z8xWo05OdrULMA9El5HSiWlqXNCw=",
      "last_login": "2017-05-31T20:46:26.344Z",
      "is_superuser": false,
      "username": "Le Poulpe",
      "first_name": "",
      "last_name": "",
      "email": "",
      "is_staff": true,
      "is_active": true,
      "date_joined": "2017-05-31T20:23:20Z",
      "groups": [],
      "user_permissions": []
    }
  },
  {
    "model": "auth.user",
    "pk": 28,
    "fields": {
      "password": "pbkdf2_sha256$36000$nKtmEKeobIqK$J3S4PKE3eJjRsA0z8xWo05OdrULMA9El5HSiWlqXNCw=",
      "last_login": "2017-05-31T20:46:26.344Z",
      "is_superuser": false,
      "username": "Emile Durkheim",
      "first_name": "",
      "last_name": "",
      "email": "",
      "is_staff": true,
      "is_active": true,
      "date_joined": "2017-05-31T20:23:20Z",
      "groups": [],
      "user_permissions": []
    }
  },
  {
    "model": "auth.user",
    "pk": 29,
    "fields": {
      "password": "pbkdf2_sha256$36000$nKtmEKeobIqK$J3S4PKE3eJjRsA0z8xWo05OdrULMA9El5HSiWlqXNCw=",
      "last_login": "2017-05-31T20:46:26.344Z",
      "is_superuser": false,
      "username": "Milhouse",
      "first_name": "",
      "last_name": "",
      "email": "",
      "is_staff": true,
      "is_active": true,
      "date_joined": "2017-05-31T20:23:20Z",
      "groups": [],
      "user_permissions": []
    }
  },
  {
    "model": "auth.user",
    "pk": 30,
    "fields": {
      "password": "pbkdf2_sha256$36000$nKtmEKeobIqK$J3S4PKE3eJjRsA0z8xWo05OdrULMA9El5HSiWlqXNCw=",
      "last_login": "2017-05-31T20:46:26.344Z",
      "is_superuser": false,
      "username": "Massive",
      "first_name": "",
      "last_name": "",
      "email": "",
      "is_staff": true,
      "is_active": true,
      "date_joined": "2017-05-31T20:23:20Z",
      "groups": [],
      "user_permissions": []
    }
  },
  {
    "model": "auth.user",
    "pk": 31,
    "fields": {
      "password": "pbkdf2_sha256$36000$nKtmEKeobIqK$J3S4PKE3eJjRsA0z8xWo05OdrULMA9El5HSiWlqXNCw=",
      "last_login": "2017-05-31T20:46:26.344Z",
      "is_superuser": false,
      "username": "Mimi",
      "first_name": "",
      "last_name": "",
      "email": "",
      "is_staff": true,
      "is_active": true,
      "date_joined": "2017-05-31T20:23:20Z",
      "groups": [],
      "user_permissions": []
    }
  }
]